{
  "items": [
    {
      "type": "binary",
      "name": "hlt",
      "state": 0,
      "icon": "camera",
      "stateVerbage": {
        "1": "open",
        "0": "closed"
      },
      "method": "hlt",
      "class": "Controller",
      "prettyName": "HLT Valve",
      "value": 0
    },
    {
      "type": "binary",
      "name": "pump",
      "state": 0,
      "icon": "camera",
      "stateVerbage": {
        "1": "on",
        "0": "off"
      },
      "method": "pump",
      "class": "Controller",
      "prettyName": "Pump",
      "value": 0
    },
    {
      "type": "binary",
      "name": "rims",
      "state": 0,
      "icon": "flash_on",
      "stateVerbage": {
        "1": "on",
        "0": "off"
      },
      "method": "pid",
      "class": "Controller",
      "prettyName": "RIMS Heater",
      "value": 0
    },
    {
      "type": "divert",
      "name": "hltDivert",
      "location": "1",
      "icon": "donut_small",
      "locationVerbage": {
        "1": "mash",
        "0": "boil"
      },
      "method": "hlt_to",
      "class": "Controller",
      "prettyName": "HLT Divert Valve",
      "value": 0
    },
    {
      "type": "divert",
      "name": "rimsDivert",
      "location": "1",
      "icon": "donut_small",
      "locationVerbage": {
        "1": "mash",
        "0": "boil"
      },
      "method": "rims_to",
      "class": "Controller",
      "prettyName": "RIMS Divert Valve",
      "value": 0
    },
    {
      "type": "method",
      "name": "sleep",
      "prettyName": "Wait",
      "icon": "hourglass_full",
      "desc": "Wait for this amount of minutes",
      "method": "sleep",
      "class": "time",
      "inputType": "tel",
      "inputLabel": "A Number...",
      "value": null
    },
    {
      "type": "method",
      "name": "watch",
      "prettyName": "Watch Until",
      "desc": "Wait until PV is equal to or greater than SV",
      "method": "watch",
      "class": "Controller",
      "icon": "search"
    },
    {
      "type": "method",
      "name": "slack",
      "prettyName": "Send in Slack",
      "desc": "Sends a message in slack",
      "icon": "send",
      "method": "send",
      "class": "Controller",
      "inputType": "text",
      "inputLabel": "A Message for Slack...",
      "value": null
    },
    {
      "type": "method",
      "name": "set_sv",
      "prettyName": "Set Target Temperature",
      "desc": "Sets the target temperature",
      "icon": "whatshot",
      "method": "set_sv",
      "class": "Controller",
      "inputType": "tel",
      "inputLabel": "Target Temperature",
      "value": null
    }
  ]
}
